rcl_logging_interface/_dummy.cpython-314t-x86_64-linux-gnu.so
ros_rcl_logging_interface-3.1.1.data/data/include/rcl_logging_interface/rcl_logging_interface/rcl_logging_interface.h
ros_rcl_logging_interface-3.1.1.data/data/include/rcl_logging_interface/rcl_logging_interface/visibility_control.h
ros_rcl_logging_interface-3.1.1.data/data/lib/librcl_logging_interface.so
ros_rcl_logging_interface-3.1.1.data/data/share/ament_index/resource_index/package_run_dependencies/rcl_logging_interface
ros_rcl_logging_interface-3.1.1.data/data/share/ament_index/resource_index/packages/rcl_logging_interface
ros_rcl_logging_interface-3.1.1.data/data/share/ament_index/resource_index/parent_prefix_path/rcl_logging_interface
ros_rcl_logging_interface-3.1.1.data/data/share/rcl_logging_interface/local_setup.bash
ros_rcl_logging_interface-3.1.1.data/data/share/rcl_logging_interface/local_setup.dsv
ros_rcl_logging_interface-3.1.1.data/data/share/rcl_logging_interface/local_setup.sh
ros_rcl_logging_interface-3.1.1.data/data/share/rcl_logging_interface/local_setup.zsh
ros_rcl_logging_interface-3.1.1.data/data/share/rcl_logging_interface/package.dsv
ros_rcl_logging_interface-3.1.1.data/data/share/rcl_logging_interface/package.xml
ros_rcl_logging_interface-3.1.1.data/data/share/rcl_logging_interface/cmake/ament_cmake_export_dependencies-extras.cmake
ros_rcl_logging_interface-3.1.1.data/data/share/rcl_logging_interface/cmake/ament_cmake_export_include_directories-extras.cmake
ros_rcl_logging_interface-3.1.1.data/data/share/rcl_logging_interface/cmake/ament_cmake_export_targets-extras.cmake
ros_rcl_logging_interface-3.1.1.data/data/share/rcl_logging_interface/cmake/rcl_logging_interfaceConfig-version.cmake
ros_rcl_logging_interface-3.1.1.data/data/share/rcl_logging_interface/cmake/rcl_logging_interfaceConfig.cmake
ros_rcl_logging_interface-3.1.1.data/data/share/rcl_logging_interface/cmake/rcl_logging_interfaceExport-release.cmake
ros_rcl_logging_interface-3.1.1.dist-info/METADATA
ros_rcl_logging_interface-3.1.1.dist-info/WHEEL
ros_rcl_logging_interface-3.1.1.dist-info/top_level.txt
ros_rcl_logging_interface-3.1.1.dist-info/RECORD
