Metadata-Version: 2.4
Name: ros-rcl-logging-interface
Version: 3.1.1
Summary: Wheel for the rcl_logging_interface (ros-rcl-logging-interface) ROS 2 package.
Requires-Dist: ros-rcutils~=6.7.4
Dynamic: description
Dynamic: description-content-type
Dynamic: requires-dist
Dynamic: summary
